xxgb/__init__.py
xxgb/decompose.py
xxgb/monotonefeature.py
xxgb/reduction.py
xxgb/wrapper.py
xxgb/experiments/__init__.py
xxgb/experiments/actionability.py
xxgb/experiments/actionability_inversed.py
xxgb/experiments/compare_rf.py
xxgb/experiments/corner_cases.py
xxgb/experiments/counting.py
xxgb/experiments/far_close.py
xxgb/experiments/lof.py
xxgb/experiments/proximity.py
xxgb/experiments/sensitivity.py
xxgb/xps/__init__.py
xxgb/xps/api.py
xxgb/xps/attribution/__init__.py
xxgb/xps/attribution/api.py
xxgb/xps/attribution/better.py
xxgb/xps/attribution/cf.py
xxgb/xps/attribution/cf_summary.py
xxgb/xps/attribution/easy.py
xxgb/xps/attribution/integrated.py
xxgb/xps/attribution/lime_wrapper.py
xxgb/xps/attribution/linear_gradient.py
xxgb/xps/attribution/opposite.py
xxgb/xps/attribution/tree.py
xxgb/xps/attribution/utils.py
xxgb/xps/attribution/group/__init__.py
xxgb/xps/attribution/group/exponential.py
xxgb/xps/attribution/group/sum_explainer.py
xxgb/xps/counterfactuals/__init__.py
xxgb/xps/counterfactuals/api.py
xxgb/xps/counterfactuals/composition.py
xxgb/xps/counterfactuals/cone.py
xxgb/xps/counterfactuals/face.py
xxgb/xps/counterfactuals/knn.py
xxgb/xps/counterfactuals/opposite.py
xxgb/xps/counterfactuals/focus/__init__.py
xxgb/xps/counterfactuals/focus/hinge.py
xxgb/xps/counterfactuals/focus/model.py
xxgb/xps/counterfactuals/focus/trees.py
xxgb/xps/counterfactuals/focus/xgb.py
xxgb/xps/counterfactuals/tolomei/__init__.py
xxgb/xps/counterfactuals/tolomei/model.py
xxgb/xps/counterfactuals/tolomei/utils.py
emxps-0.0.6.dist-info/LICENSE
emxps-0.0.6.dist-info/METADATA
emxps-0.0.6.dist-info/WHEEL
emxps-0.0.6.dist-info/top_level.txt
emxps-0.0.6.dist-info/RECORD
