Metadata-Version: 2.1
Name: emxps
Version: 0.0.6
Summary: Miscellanous Explanation Methods
Home-page: https://github.com/emanuele-albini/emxps
Author: Emanuele Albini
License: UNKNOWN
Project-URL: Documentation, https://emanuele-albini.github.io/emxps
Project-URL: Source Code, https://github.com/emanuele-albini/emxps
Project-URL: Bug Tracker, https://github.com/emanuele-albini/emxps/issues
Project-URL: Author Website, https://www.emanuelealbini.com
Keywords: XAI,Explainability,Explainable,AI,Counterfactual,Algorithmic Recourse,Contrastive Explanations,Feature Importance,Feature Attribution
Platform: any
Classifier: Programming Language :: Python :: 3
Classifier: Programming Language :: Python :: 3.6
Classifier: Programming Language :: Python :: 3.7
Classifier: Programming Language :: Python :: 3.8
Classifier: Programming Language :: Python :: 3.9
Classifier: Operating System :: OS Independent
Classifier: License :: OSI Approved :: MIT License
Classifier: Development Status :: 4 - Beta
Requires-Python: >=3.6
License-File: LICENSE
Requires-Dist: emutils
Requires-Dist: numpy
Requires-Dist: scipy
Requires-Dist: pandas
Requires-Dist: networkx
Requires-Dist: xgboost
Requires-Dist: scikit-learn
Requires-Dist: dataclasses
Requires-Dist: tqdm
Requires-Dist: joblib
Requires-Dist: plotly
Requires-Dist: statsmodels
Requires-Dist: lime (==0.2.0.1)
Requires-Dist: shap (==0.39.0)
